LICENSE
MANIFEST.in
README.md
requirements.txt
setup.py
discord/ext/wizard/__init__.py
discord/ext/wizard/checks.py
discord/ext/wizard/converters.py
discord/ext/wizard/mixins.py
discord/ext/wizard/prompt.py
discord/ext/wizard/wizard.py
discord_ext_wizard.egg-info/PKG-INFO
discord_ext_wizard.egg-info/SOURCES.txt
discord_ext_wizard.egg-info/dependency_links.txt
discord_ext_wizard.egg-info/requires.txt
discord_ext_wizard.egg-info/top_level.txt